actool/__init__.py
actool/network/__init__.py
actool/network/get_ip.py
actool-0.0.2.dist-info/METADATA
actool-0.0.2.dist-info/WHEEL
actool-0.0.2.dist-info/entry_points.txt
actool-0.0.2.dist-info/RECORD
