Metadata-Version: 2.1
Name: actool
Version: 0.0.2
Summary: 
Home-page: https://github.com/NullPointExceptionForEveryone/actool
License: MIT
Keywords: actool
Author: pfy
Author-email: program_yun@163.com
Requires-Python: >=3.11,<4.0
Classifier: License :: OSI Approved :: MIT License
Classifier: Programming Language :: Python :: 3
Classifier: Programming Language :: Python :: 3.11
Classifier: Programming Language :: Python :: 3.12
Requires-Dist: requests (>=2.32.3,<3.0.0)
Project-URL: Repository, https://github.com/NullPointExceptionForEveryone/actool
